{
    "Afghanistan": 39835.43,
    "Albania": 2811.67,
    "Algeria": 44616.63,
    "American Samoa": 55.10,
    "Andorra": 77.35,
    "Angola": 33933.61,
    "Antigua and Barbuda": 98.73,
    "Argentina": 45808.75,
    "Armenia": 2968.13,
    "Aruba": 107.19,
    "Australia": 25739.26,
    "Austria": 8956.28,
    "Azerbaijan": 10145.21,
    "Bahamas The": 396.91,
    "Bahrain": 1748.30,
    "Bangladesh": 166303.49,
    "Barbados": 287.71,
    "Belarus": 9340.31,
    "Belgium": 11587.88,
    "Belize": 404.92,
    "Benin": 12451.03,
    "Bermuda": 63.87,
    "Bhutan": 779.90,
    "Bolivia": 11832.94,
    "Bosnia and Herzegovina": 3263.46,
    "Botswana": 2397.24,
    "Brazil": 213993.44,
    "Brunei Darussalam": 441.53,
    "Bulgaria": 6899.13,
    "Burkina Faso": 21497.10,
    "Burundi": 12255.43,
    "Cabo Verde": 561.90,
    "Cambodia": 16946.45,
    "Cameroon": 27224.26,
    "Canada": 38246.11,
    "Cayman Islands": 66.50,
    "Central African Republic": 4919.99,
    "Chad": 16914.99,
    "Channel Islands": 175.24,
    "Chile": 19212.36,
    "China": 1411100.00,
    "Colombia": 51265.84,
    "Comoros": 888.46,
    "Congo Dem. Rep.": 92377.99,
    "Congo Rep.": 5657.02,
    "Costa Rica": 5139.05,
    "Cote d'Ivoire": 27053.63,
    "Croatia": 3899.00,
    "Cuba": 11317.50,
    "Cyprus": 1215.59,
    "Czechia": 10703.45,
    "Denmark": 5856.73,
    "Djibouti": 1002.20,
    "Dominican Republic": 10953.71,
    "Ecuador": 17888.47,
    "Egypt Arab Rep.": 104258.33,
    "El Salvador": 6518.50,
    "Equatorial Guinea": 1449.89,
    "Eritrea": 3213.97,
    "Estonia": 1329.25,
    "Eswatini": 1172.37,
    "Ethiopia": 117876.23,
    "Faroe Islands": 49.05,
    "Fiji": 902.90,
    "Finland": 5541.70,
    "France": 67499.34,
    "French Polynesia": 282.53,
    "Gabon": 2278.83,
    "Gambia The": 2486.94,
    "Georgia": 3708.61,
    "Germany": 83129.29,
    "Ghana": 31732.13,
    "Greece": 10664.57,
    "Greenland": 56.65,
    "Grenada": 113.02,
    "Guam": 170.18,
    "Guatemala": 17109.75,
    "Guinea": 13497.24,
    "Guinea-Bissau": 2015.49,
    "Guyana": 790.33,
    "Haiti": 11541.68,
    "Honduras": 10062.99,
    "Hong Kong SAR China": 7413.10,
    "Hungary": 9709.89,
    "Iceland": 372.30,
    "India": 1393409.03,
    "Indonesia": 276361.79,
    "Iran Islamic Rep.": 85028.76,
    "Iraq": 41179.35,
    "Ireland": 5028.23,
    "Israel": 9364.00,
    "Italy": 59066.22,
    "Jamaica": 2973.46,
    "Japan": 125681.59,
    "Jordan": 10269.02,
    "Kazakhstan": 19002.59,
    "Kenya": 54985.70,
    "Kiribati": 121.39,
    "Korea Dem. People's Rep.": 25887.04,
    "Korea Rep.": 51744.88,
    "Kosovo": 1806.28,
    "Kuwait": 4328.55,
    "Kyrgyz Republic": 6694.20,
    "Lao PDR": 7379.36,
    "Latvia": 1883.16,
    "Lebanon": 6769.15,
    "Lesotho": 2159.07,
    "Liberia": 5180.21,
    "Libya": 6958.54,
    "Liechtenstein": 38.25,
    "Lithuania": 2795.32,
    "Luxembourg": 639.07,
    "Macao SAR China": 658.39,
    "Madagascar": 28427.33,
    "Malawi": 19647.68,
    "Malaysia": 32776.19,
    "Maldives": 543.62,
    "Mali": 20855.72,
    "Malta": 516.87,
    "Mauritania": 4775.11,
    "Mauritius": 1266.06,
    "Mexico": 130262.22,
    "Micronesia Fed. Sts.": 116.25,
    "Monaco": 39.52,
    "Moldova": 2573.93,
    "Mongolia": 3329.28,
    "Montenegro": 620.17,
    "Morocco": 37344.79,
    "Mozambique": 32163.04,
    "Myanmar": 54806.01,
    "Namibia": 2587.34,
    "Nepal": 29674.92,
    "Netherlands": 17533.40,
    "New Caledonia": 272.62,
    "New Zealand": 5122.60,
    "Nicaragua": 6702.38,
    "Niger": 25130.81,
    "Nigeria": 211400.70,
    "North Macedonia": 2065.09,
    "Northern Mariana Islands": 57.91,
    "Norway": 5408.32,
    "Oman": 5223.38,
    "Pakistan": 225199.93,
    "Palau": 18.17,
    "Panama": 4381.58,
    "Papua New Guinea": 9119.00,
    "Paraguay": 7219.64,
    "Peru": 33359.42,
    "Philippines": 111046.91,
    "Poland": 37781.02,
    "Portugal": 10299.42,
    "Puerto Rico": 3263.58,
    "Qatar": 2930.52,
    "Romania": 19115.15,
    "Russian Federation": 143446.06,
    "Rwanda": 13276.52,
    "Samoa": 200.14,
    "San Marino": 34.01,
    "Sao Tome and Principe": 223.36,
    "Saudi Arabia": 35340.68,
    "Senegal": 17196.31,
    "Serbia": 6844.08,
    "Seychelles": 99.20,
    "Sierra Leone": 8141.34,
    "Singapore": 5453.57,
    "Slovak Republic": 5447.25,
    "Slovenia": 2107.01,
    "Solomon Islands": 704.00,
    "Somalia": 16359.50,
    "South Africa": 60042.00,
    "South Sudan": 11381.38,
    "Spain": 47326.69,
    "Sri Lanka": 22156.00,
    "St. Kitts and Nevis": 53.55,
    "St. Lucia": 184.40,
    "St. Martin (French part)": 39.24,
    "St. Vincent and the Grenadines": 111.27,
    "Sudan": 44909.35,
    "Suriname": 591.80,
    "Sweden": 10415.81,
    "Switzerland": 8697.72,
    "Syrian Arab Republic": 18275.70,
    "Tajikistan": 9749.63,
    "Tanzania": 61498.44,
    "Thailand": 69950.84,
    "Timor-Leste": 1343.88,
    "Togo": 8478.24,
    "Tonga": 106.76,
    "Trinidad and Tobago": 1403.37,
    "Tunisia": 11935.76,
    "Turkiye": 85042.74,
    "Turkmenistan": 6117.93,
    "Uganda": 47123.53,
    "Ukraine": 43814.58,
    "United Arab Emirates": 9991.08,
    "United Kingdom": 67326.57,
    "United States": 331893.74,
    "Uruguay": 3485.15,
    "Uzbekistan": 34915.10,
    "Vanuatu": 314.46,
    "Venezuela RB": 28704.95,
    "Vietnam": 98168.83,
    "Virgin Islands (U.S.)": 105.87,
    "Yemen Rep.": 30490.64,
    "Zambia": 18920.66,
    "Zimbabwe": 15092.17,
    "Taiwan": 23186.28
}